<?xml version="1.0" encoding="utf-8" ?>
<dwsync>
<file name="bullet_1.png" server="bss.com.ve//httpdocs/new_bss/" local="129481518524755221" remote="129492057600000000" />
<file name="bullet_2.png" server="bss.com.ve//httpdocs/new_bss/" local="127866900000000000" remote="129492057600000000" />
<file name="bullet_3.png" server="bss.com.ve//httpdocs/new_bss/" local="127866900000000000" remote="129492057600000000" />
<file name="bullet_4.png" server="bss.com.ve//httpdocs/new_bss/" local="127866900020000000" remote="129492057600000000" />
<file name="bullet_5.png" server="bss.com.ve//httpdocs/new_bss/" local="127866900020000000" remote="129492057600000000" />
<file name="bullet_6.png" server="bss.com.ve//httpdocs/new_bss/" local="127866900040000000" remote="129492057600000000" />
<file name="bullet_7.png" server="bss.com.ve//httpdocs/new_bss/" local="127866900080000000" remote="129492057600000000" />
<file name="bullet_8.png" server="bss.com.ve//httpdocs/new_bss/" local="129491728759882816" remote="129492057600000000" />
<file name="bullet_1.png" server="bss.com.ve//httpdocs/" local="129481518524755221" remote="129511077600000000" />
<file name="bullet_2.png" server="bss.com.ve//httpdocs/" local="127866900000000000" remote="129511077600000000" />
<file name="bullet_3.png" server="bss.com.ve//httpdocs/" local="127866900000000000" remote="129511077600000000" />
<file name="bullet_4.png" server="bss.com.ve//httpdocs/" local="127866900020000000" remote="129511077600000000" />
<file name="bullet_5.png" server="bss.com.ve//httpdocs/" local="127866900020000000" remote="129511077600000000" />
<file name="bullet_6.png" server="bss.com.ve//httpdocs/" local="127866900040000000" remote="129511077600000000" />
<file name="bullet_7.png" server="bss.com.ve//httpdocs/" local="127866900080000000" remote="129511077600000000" />
<file name="bullet_8.png" server="bss.com.ve//httpdocs/" local="129491728759882816" remote="129511077600000000" />
<file name="required.png" server="bss.com.ve//httpdocs/" local="128327431300000000" remote="129511077600000000" />
</dwsync>